dash_ketcher/DashKetcher.py
dash_ketcher/__init__.py
dash_ketcher/_imports_.py
dash_ketcher/dash_ketcher.min.js
dash_ketcher/dash_ketcher.min.js.map
dash_ketcher/metadata.json
dash_ketcher/package-info.json
dash_ketcher-0.1.dist-info/licenses/LICENSE
dash_ketcher-0.1.dist-info/METADATA
dash_ketcher-0.1.dist-info/WHEEL
dash_ketcher-0.1.dist-info/top_level.txt
dash_ketcher-0.1.dist-info/RECORD
