Metadata-Version: 2.4
Name: dash_ketcher
Version: 0.1
Summary: Dash Ketcher is a component allowing to use Ketcher molecules drawer in Dash.
Author: Philippe Gantzer <p.gantzer@icredd.hokudai.ac.jp>
License: MIT
Classifier: Framework :: Dash
Classifier: Topic :: Scientific/Engineering :: Chemistry
Classifier: Development Status :: 4 - Beta
Classifier: Programming Language :: Python
Classifier: Programming Language :: Python :: 3
Classifier: Programming Language :: Python :: 3 :: Only
License-File: LICENSE
Dynamic: author
Dynamic: classifier
Dynamic: description
Dynamic: description-content-type
Dynamic: license
Dynamic: license-file
Dynamic: summary
